[
  {
    "id": "ff895c09-d15a-40fb-87be-1f413a069dfb",
    "idSantri": "715c506e-c7d7-4a71-8fcc-f2bc52cb4e88",
    "baru": [1],
    "juziyah": [],
    "syahadah": [],
    "baruTerakhir": 1,
    "baruTerkecil": 1,
    "juziyahTerkecil": null,
    "syahadahTerkecil": null,
    "baruMerah": false,
    "juziyahMerah": false,
    "syahadahMerah": false
  },
  {
    "id": "f3d804b9-c306-4351-be5b-23df5b8ae033",
    "idSantri": "9b73c088-795e-4d0f-9ced-6eb7d3187665",
    "baru": [1],
    "juziyah": [],
    "syahadah": [],
    "baruTerakhir": 1,
    "baruTerkecil": 1,
    "juziyahTerkecil": null,
    "syahadahTerkecil": null,
    "baruMerah": false,
    "juziyahMerah": false,
    "syahadahMerah": false
  }
]
